[
  {
    "type": "major",
    "name_short": "ar01",
    "name": "The Magician",
    "value": "1",
    "value_int": 1,
    "meaning_up": "Skill, diplomacy, address, subtlety; sickness, pain, loss, disaster, snares of enemies; self-confidence, will; the Querent, if male.",
    "meaning_rev": "Physician, Magus, mental disease, disgrace, disquiet."
  },
  {
    "name": "The Magician",
    "desc": "Xavier"
  },
  {
    "name": "The High Priestess",
    "desc": "Xavier"
  },
  {
    "name": "The Empress",
    "desc": "Xavier"
  },
  {
    "name": "The Emperor",
    "desc": "Xavier"
  },
  {
    "name": "The Hierophant",
    "desc": "Xavier"
  },
  {
    "name": "The Lovers",
    "desc": "Xavier"
  },
  {
    "name": "The Chariot",
    "desc": "Xavier"
  },
  {
    "name": "Strength",
    "desc": "Xavier"
  },
  {
    "name": "The Hermit",
    "desc": "Xavier"
  },
  {
    "name": "Wheel of Fortune",
    "desc": "Xavier"
  },
  {
    "name": "Justice",
    "desc": "Xavier"
  },
  {
    "name": "The Hanged Man",
    "desc": "Xavier"
  },
  {
    "name": "Death",
    "desc": "Xavier"
  },
  {
    "name": "Temperance",
    "desc": "Xavier"
  },
  {
    "name": "The Devil",
    "desc": "Xavier"
  },
  {
    "name": "The Tower",
    "desc": "Xavier"
  },
  {
    "name": "The Star",
    "desc": "Xavier"
  },
  {
    "name": "The Moon",
    "desc": "Xavier"
  },
  {
    "name": "The Sun",
    "desc": "Xavier"
  },
  {
    "name": "Judgment",
    "desc": "Xavier"
  }
]
